AUTHORS.md
LICENSE
README.md
pyproject.toml
setup.cfg
setup.py
rele/__init__.py
rele/__main__.py
rele/apps.py
rele/client.py
rele/config.py
rele/discover.py
rele/middleware.py
rele/publishing.py
rele/subscription.py
rele/worker.py
rele/contrib/__init__.py
rele/contrib/django_db_middleware.py
rele/contrib/flask_middleware.py
rele/contrib/logging_middleware.py
rele/contrib/unrecoverable_middleware.py
rele/management/__init__.py
rele/management/discover.py
rele/management/commands/__init__.py
rele/management/commands/runrele.py
rele/management/commands/showsubscriptions.py
rele_les_transformations.egg-info/PKG-INFO
rele_les_transformations.egg-info/SOURCES.txt
rele_les_transformations.egg-info/dependency_links.txt
rele_les_transformations.egg-info/entry_points.txt
rele_les_transformations.egg-info/not-zip-safe
rele_les_transformations.egg-info/requires.txt
rele_les_transformations.egg-info/top_level.txt
tests/commands/__init__.py
tests/commands/test_runrele.py
tests/commands/test_showsubscriptions.py
tests/more_subs/__init__.py
tests/more_subs/subs.py